.editorconfig
.gitignore
.gitlab-ci.yml
LICENSE
README.rst
publish.settings.sh
publish.sh
pyproject.toml
.idea/modules.xml
.idea/peek-admin-app.iml
.idea/inspectionProfiles/Project_Default.xml
.idea/inspectionProfiles/profiles_settings.xml
peek_admin_app/.browserslistrc
peek_admin_app/.gitignore
peek_admin_app/README.md
peek_admin_app/__init__.py
peek_admin_app/angular.json
peek_admin_app/package-lock.json
peek_admin_app/package.json
peek_admin_app/proxy.conf.json
peek_admin_app/tsconfig.app.json
peek_admin_app/tsconfig.json
peek_admin_app/tsconfig.spec.json
peek_admin_app/tsconfig.worker.json
peek_admin_app.egg-info/PKG-INFO
peek_admin_app.egg-info/SOURCES.txt
peek_admin_app.egg-info/dependency_links.txt
peek_admin_app.egg-info/requires.txt
peek_admin_app.egg-info/top_level.txt
peek_admin_app/src/_components.scss
peek_admin_app/src/_variables.scss
peek_admin_app/src/app.module.ts
peek_admin_app/src/favicon.ico
peek_admin_app/src/index.html
peek_admin_app/src/main.ts
peek_admin_app/src/polyfills.ts
peek_admin_app/src/styles.scss
peek_admin_app/src/test.ts
peek_admin_app/src/typings.d.ts
peek_admin_app/src/app/app-routing.module.ts
peek_admin_app/src/app/plugin-root.component.ts
peek_admin_app/src/app/components/app-component/app.component.html
peek_admin_app/src/app/components/app-component/app.component.scss
peek_admin_app/src/app/components/app-component/app.component.spec.ts
peek_admin_app/src/app/components/app-component/app.component.ts
peek_admin_app/src/app/components/dashboard/dashboard.component.html
peek_admin_app/src/app/components/dashboard/dashboard.component.scss
peek_admin_app/src/app/components/dashboard/dashboard.component.spec.ts
peek_admin_app/src/app/components/dashboard/dashboard.component.ts
peek_admin_app/src/app/components/dashboard-stats/dashboard-stats.component.html
peek_admin_app/src/app/components/dashboard-stats/dashboard-stats.component.scss
peek_admin_app/src/app/components/dashboard-stats/dashboard-stats.component.spec.ts
peek_admin_app/src/app/components/dashboard-stats/dashboard-stats.component.ts
peek_admin_app/src/app/components/navbar/navbar.component.html
