Metadata-Version: 2.4
Name: peek-admin-app
Version: 5.0.4
Summary: Peek Admin App - the Angular Web build environment for Peek Admin
Author-email: Synerty <contact@synerty.com>
Project-URL: Homepage, https://github.com/Synerty/peek-admin-app
Keywords: Peek,Python,Platform,synerty
License-File: LICENSE
Requires-Dist: peek-plugin-base==5.0.4
Dynamic: license-file
